enterpret_claims_extractor/__init__.py
enterpret_claims_extractor/config.py
enterpret_claims_extractor/exceptions.py
enterpret_claims_extractor/extractor.py
enterpret_claims_extractor/prompts.py
enterpret_claims_extractor/utils.py
enterpret_claims_extractor-0.1.2.dist-info/METADATA
enterpret_claims_extractor-0.1.2.dist-info/WHEEL
enterpret_claims_extractor-0.1.2.dist-info/top_level.txt
enterpret_claims_extractor-0.1.2.dist-info/RECORD
